brevian/__init__.py
brevian/client.py
brevian/core/__init__.py
brevian/core/api_error.py
brevian/core/client_wrapper.py
brevian/core/datetime_utils.py
brevian/core/jsonable_encoder.py
brevian/core/remove_none_from_dict.py
brevian/errors/__init__.py
brevian/errors/bad_request_error.py
brevian/errors/forbidden_error.py
brevian/errors/internal_server_error.py
brevian/errors/not_found_error.py
brevian/errors/too_many_requests_error.py
brevian/types/__init__.py
brevian/types/chat_request.py
brevian/types/chat_request_messages_item.py
brevian/types/choice.py
brevian/types/choice_message.py
brevian/types/error_response.py
brevian/types/forbidden_error_body.py
brevian/types/internal_server_error_body.py
brevian/types/message.py
brevian/types/message_role_enum.py
brevian/types/post_chat_request_messages_item.py
brevian/types/post_chat_request_messages_item_role.py
brevian/types/post_chat_response.py
brevian/types/post_chat_response_choices_item.py
brevian/types/post_chat_response_choices_item_message.py
brevian/types/post_chat_response_usage.py
brevian/types/sub_query_metadata.py
brevian/types/too_many_requests_error_body.py
brevian/types/unified_citation.py
brevian/types/usage.py
brevian-0.1.4.dist-info/LICENSE
brevian-0.1.4.dist-info/METADATA
brevian-0.1.4.dist-info/WHEEL
brevian-0.1.4.dist-info/RECORD
